{
  "generated_at": "2026-07-21T10:31:20.513601Z",
  "models": [
    {
      "canonical_slug": "kwaipilot/kat-coder-air-v2.5-20260710",
      "created": 1783714590,
      "detected_at": "2026-07-20T21:31:00.910691Z",
      "model_id": "kwaipilot/kat-coder-air-v2.5:free",
      "name": "Kwaipilot: KAT-Coder-Air V2.5 (free)"
    },
    {
      "canonical_slug": "meituan/longcat-2.0-20260720",
      "created": 1784554658,
      "detected_at": "2026-07-20T14:01:04.767294Z",
      "model_id": "meituan/longcat-2.0",
      "name": "Meituan: LongCat 2.0"
    }
  ],
  "window_hours": 24
}